{
  "/favicon.ico/route": "app/favicon.ico/route.js",
  "/_not-found/page": "app/_not-found/page.js",
  "/blog/parlance-ai-agent/page": "app/blog/parlance-ai-agent/page.js",
  "/about/page": "app/about/page.js",
  "/blog/page": "app/blog/page.js",
  "/blog/mortgage-lead-generation/page": "app/blog/mortgage-lead-generation/page.js",
  "/business-grants/page": "app/business-grants/page.js",
  "/business-loans/page": "app/business-loans/page.js",
  "/life-insurance/page": "app/life-insurance/page.js",
  "/car-finance/page": "app/car-finance/page.js",
  "/careers/account-strategist/page": "app/careers/account-strategist/page.js",
  "/page": "app/page.js",
  "/mortgage/page": "app/mortgage/page.js",
  "/careers/creative-strategist/page": "app/careers/creative-strategist/page.js",
  "/careers/data-analyst/page": "app/careers/data-analyst/page.js",
  "/property-investment/page": "app/property-investment/page.js",
  "/secured-loans/page": "app/secured-loans/page.js",
  "/roi/page": "app/roi/page.js",
  "/careers/page": "app/careers/page.js",
  "/privacy-policy/page": "app/privacy-policy/page.js",
  "/cookies/page": "app/cookies/page.js",
  "/terms-conditions/page": "app/terms-conditions/page.js",
  "/get-started/page": "app/get-started/page.js",
  "/success/page": "app/success/page.js"
}